botw_havok/__init__.py
botw_havok/havok.py
botw_havok/hkfile.py
botw_havok/binary/__init__.py
botw_havok/binary/base.py
botw_havok/binary/reader.py
botw_havok/binary/types.py
botw_havok/binary/writer.py
botw_havok/classes/StaticCompoundInfo.py
botw_havok/classes/__init__.py
botw_havok/classes/base.py
botw_havok/classes/hkRootLevelContainer.py
botw_havok/classes/hkaiDirectedGraphExplicitCost.py
botw_havok/classes/hkaiNavMesh.py
botw_havok/classes/hkaiStaticTreeNavMeshQueryMediator.py
botw_havok/classes/hkcdStaticAabbTree.py
botw_havok/classes/hkcdStaticTreeDefaultTreeStorage6.py
botw_havok/classes/hkpBoxShape.py
botw_havok/classes/hkpBvCompressedMeshShape.py
botw_havok/classes/hkpCapsuleShape.py
botw_havok/classes/hkpConvexTransformShape.py
botw_havok/classes/hkpConvexTranslateShape.py
botw_havok/classes/hkpConvexVerticesShape.py
botw_havok/classes/hkpCylinderShape.py
botw_havok/classes/hkpListShape.py
botw_havok/classes/hkpPhysicsData.py
botw_havok/classes/hkpPhysicsSystem.py
botw_havok/classes/hkpRigidBody.py
botw_havok/classes/hkpSphereShape.py
botw_havok/classes/hkpStaticCompoundShape.py
botw_havok/classes/common/ActorInfo.py
botw_havok/classes/common/ShapeInfo.py
botw_havok/classes/common/__init__.py
botw_havok/classes/common/hkAabb.py
botw_havok/classes/common/hkBaseObject.py
botw_havok/classes/common/hkLocalFrame.py
botw_havok/classes/common/hkMotionState.py
botw_havok/classes/common/hkMultiThreadCheck.py
botw_havok/classes/common/hkObject.py
botw_havok/classes/common/hkReferencedObject.py
botw_havok/classes/common/hkRootLevelContainerNamedVariant.py
botw_havok/classes/common/hkSimpleProperty.py
botw_havok/classes/common/hkSimplePropertyValue.py
botw_havok/classes/common/hkUFloat8.py
botw_havok/classes/common/hkaiDirectedGraphExplicitCostEdge.py
botw_havok/classes/common/hkaiDirectedGraphExplicitCostNode.py
botw_havok/classes/common/hkaiNavMeshEdge.py
botw_havok/classes/common/hkaiNavMeshFace.py
botw_havok/classes/common/hkaiNavMeshQueryMediator.py
botw_havok-0.3.18.dist-info/METADATA
botw_havok-0.3.18.dist-info/WHEEL
botw_havok-0.3.18.dist-info/entry_points.txt
botw_havok-0.3.18.dist-info/top_level.txt
botw_havok-0.3.18.dist-info/RECORD
