Metadata-Version: 2.1
Name: botw-havok
Version: 0.3.18
Summary: A library for manipulating Breath of the Wild Havok packfiles
Home-page: https://github.com/krenyy/botw_havok
Author: kreny
Author-email: kronerm9@gmail.com
License: UNKNOWN
Platform: UNKNOWN
Classifier: Programming Language :: Python :: 3 :: Only
Classifier: License :: OSI Approved :: GNU General Public License v3 or later (GPLv3+)
Classifier: Operating System :: OS Independent
Requires-Python: >=3.6
Requires-Dist: colorama (~=0.4.3)
Requires-Dist: numpy (~=1.19.2)
Requires-Dist: oead (~=1.2.0)
